division_perm
