Metadata-Version: 1.0
Name: sw-django-perm-division
Version: 0.0.11
Summary: Soft Way company permission system based on employee division affiliations.
Home-page: https://github.com/telminov/sw-django-division-perm
Author: Telminov Sergey
Author-email: sergey@telminov.ru
License: The MIT License
Platform: UNKNOWN
